register_file.v
module register_file (
    input clk, reset,
    input [4:0] rs1, rs2, rd,
    input [31:0] write_data_dm, // Data coming from memory
    input lw, lwi, jmp, sw,
    input [11:0] lw_imm_val, // Immediate offset for load word
    input [31:0] return_address,
    input beq, bneq, blt, bltu, bge, bgeu,

    output [31:0] src1, src2,
    output [4:0] read_data_addr_dm,
    output reg [31:0] data_out_dm,
    output [31:0] effective_value // Effective address output for memory
);
    reg [31:0] reg_mem[31:0];
    integer i;
    reg branch;

    assign read_data_addr_dm = rd;
    assign effective_value = reg_mem[rs1] + lw_imm_val; // Calculate effective address

    always @(posedge clk) begin
        if (reset) begin
            // Initialize all registers to 0
            for (i = 0; i < 32; i = i + 1) begin
                reg_mem[i] = 0;
            end
            data_out_dm = 0; // Reset data_out_dm
        end else begin
            if (lw) begin
                reg_mem[rd] = write_data_dm; // Load from memory to register
            end
            if (sw) begin
                data_out_dm = reg_mem[rs1]; // Store Word
            end else if (lwi) begin
                reg_mem[rd] = effective_value; // Load immediate address directly
            end else if (jmp) begin
                reg_mem[rd] = return_address; // Jump Address
            end
        end
    end

    // Combinational read for rs1 and rs2
    assign src1 = reg_mem[rs1];
    assign src2 = reg_mem[rs2];

endmodule

alu.v
module alu (
    input [31:0] rs1,
    input [31:0] rs2,
    input [5:0] alu_control,
    input [11:0] imm_val,
   

    output reg [31:0] result
);
     reg [4:0] shft_amnt;
     always @(*) begin
         shft_amnt <= imm_val[4:0];
     end
    always @(*) begin
        case(alu_control) begin
           6'b000000: begin
                result = rs1 + rs2;
           end
           6'b000001: begin
                result = ($signed(rs1) < $signed(rs2)) ? 1 : 0;
           end 
           6'b000010: begin
                result = (rs1 < rs2)? 1 : 0;
           end
           6'b000011; begin
                result = rs1 & rs2;
           end
           6'b000100: begin
                result = rs1 | rs2;
           end
           6'b000101: begin
                result = rs1 ^ rs2;
           end
           6'b000110: begin
                result = rs1 << rs2;
           end
           6'b000111: begin
                result = rs1 >> rs2;
           end
           6'b001000: begin
                reset = rs1 - rs2;
           end
           6'b001001: begin
                result = rs1 >>> rs2;
           end
           6'b111111: begin
               result = rs1 + imm_val;
           end
           6'111110: begin
               result = ($signed(rs1) < $signed(imm_val)) ? 1 : 0;
           end
           6'b111101: begin
               result = (rs1 < imm_val)? 1 : 0;
           end
           6'b111100: begin
               result = rs1 & rs2;
           end
           6'b111011: begin
                result = rs1 | imm_val;
           end
           6'b111010: begin
                result = rs1 ^ imm_val;
           end
           6'b111000: begin
               if(imm_val == 0000000) begin
                    result = rs1 >> shft_amnt;
               end else if (imm_val == 0100000) begin
                    result = rs1 >>> shft_amnt;
               end
           end
           
        end
        endcase
    end
    
endmodule

control_unit.v
module control_unit (
    input reset,
    input [6:0] funct7,
    input [2:0] funct3,
    input [6:0] opcode,

    output reg [5:0] alu_control, //ALU
    output reg beq, bneq, blt, bltu, bge, bgeu, //Branch
    output reg lw, lwi, sw, // Load and Store
    output reg jmp
);
    parameter R_type = 7'b0110011;
    parameter I_type = 7'b1001100;
    parameter Control_Transfer_Load_Store = 7'b1010101;

    always @(reset) begin
        if(reset) alu_control = 0;
    end    
    always @(funct7 or funct3 or opcode) begin
        case (opcode)
            R_type: begin //////////////// R_type operation ////////////////////////
                case(funct7)
                  7'b0000000: begin
                    case (funct3)
                        3'b000: begin
                            alu_control = 6'b000000; // ADD operation
                        end
                        3'b001: begin
                            alu_control = 6'b000001; // SLT operation
                        end
                        3'b010: begin
                            alu_control = 6'b000010; // SLTU operation
                        end
                        3'b011: begin
                            alu_control = 6'b000011; // AND operation
                        end
                        3'b100: begin
                            alu_control = 6'b000100; // OR operation
                        end
                        3'b101: begin
                            alu_control = 6'b000101; // XOR operation
                        end
                        3'b110: begin
                            alu_control = 6'b000110; // SLL operation
                        end
                        3'b111: begin
                            alu_control = 6'b000111; // SRL operation
                        end
                        default : ;                            
                    endcase
                    7'b0100000: begin
                        case (funct3)
                            3'b010: begin
                                alu_control = 6'b001000; // SUB operation
                            end
                            3'011: begin
                                alu_control = 6'b001001; // SRA operation
                            end
                            default: ;  
                        endcase
                    end
                  end  
                endcase
            end 
/////////////////////////////////I_type/////////////////////////////////
            I_type: begin
                case(funct3)
                    3'b000: begin
                            alu_control = 6'b111111; // ADDI operation
                        end
                        3'b001: begin
                            alu_control = 6'b111110; // SLTI operation
                        end
                        3'b010: begin
                            alu_control = 6'b111101; // SLTUI operation
                        end
                        3'b011: begin
                            alu_control = 6'111100; // ANDI operation
                        end
                        3'b100: begin
                            alu_control = 6'b111011; // ORI operation
                        end
                        3'b101: begin
                            alu_control = 6'b111010; // XORI operation
                        end
                        3'b110: begin
                            alu_control = 6'b111001; // SLLI operation
                        end
                        3'b111: begin
                            alu_control = 6'b111000; // SRLI or SRAI operation 
                        end
                        default : ; 
                endcase
            end
            Control_Transfer_Load_Store: begin
                case (funct3)
                    3'b000: begin
                       jmp = 1'b1; 
                    end
                    3'b001: begin
                        beq = 1'b1;
                    end
                    3'b010: begin
                        bneq: 1'b1;
                    end
                    3'b011: begin
                        blt = 1'b1;
                    end
                    3'b100: begin
                        bltu = 1'b1;
                    end
                    3'b101: begin
                        bge = 1'b1;
                    end
                    3'b110: begin
                        bgeu = 1'b1;
                    end
                    3'b111: begin
                        case (funct7)
                            7'b1111111: begin
                                lwi = 1'b1;
                            end
                            7'b0001000: begin
                                sw = 1'b1;
                            end
                            7'b0000000: begin
                                lw = 1'b1;
                            end
                        endcase
                    end
                    default: ;
                endcase
            end
            
            default: ;

        endcase
    end
endmodule

instruction_memory.v
module instruction_memory (
    input clk, reset,
    input [31:0] pc,

    output [31:0] instruction_code
);
    reg [8:0] memory [127:0]; 
    assign instruction_code <= {memory[pc+3], memory[pc+2], memory[pc+1], memory[pc]};

    always @(posedge clk ) begin
        if (reset) begin
//////////////////////////////////////////////////////Integer R-Type Instructions//////////////////////////////////////////////////////////
/*  In this implementation of RISC-V in the given code, integer register operations are carried out by x1, x2, and x3 registers
    where operands for operation are x1 and x2 and destination to store the result is x3.
            register mapping x1 = 5'b00001
                             x2 = 5'b00010
                             x3 = 5'b00011
            funct3:  ADD  = 000
                     SLT  = 001
                     SLTU = 010
                     AND  = 011
                     OR   = 100
                     XOR  = 101
                     SLL  = 110
                     SRL  = 111
Hence the instruction becomes  (0000 000)(0 0010) (0000 1)(000 - 111) (0001 1)(011 0011) -> (funct7)(src2)(src1)(funct3)(rd)(opcode)

Similarly for the R-type instruction SUB and SLA
funct7 = 0100 000 and 
           funct3:   SUB  = 010
                     SLA  = 011
Hence the instruction becomes  (0100 000)(0 0010) (0000 1)(000 - 111) (0001 1)(011 0011) -> (funct7)(src2)(src1)(funct3)(rd)(opcode)
*/
              
// ADD = 0x002081B3 
           memory[3] = 8'h00;
           memory[2] = 8'h20;
           memory[1] = 8'h81;
           memory[0] = 8'hB3;

//  SLT = 0x002091B3        
            memory[7] = 8'h00;
            memory[6] = 8'h20;
            memory[5] = 8'h91;
            memory[4] = 8'hB3;

// SLTU = 0x0020A1B3
            memory[11] = 8'h00;
            memory[10] = 8'h20;
            memory[9] = 8'hA1;
            memory[8] = 8'hB3;

// AND = 0x0020B1B3
            memory[15] = 8'h00;
            memory[14] = 8'h20;
            memory[13] = 8'hB1;
            memory[12] = 8'hB3;

// OR = 0x0020C1B3
            memory[19] = 8'h00;
            memory[18] = 8'h20;
            memory[17] = 8'hC1;
            memory[16] = 8'hB3;

// XOR = 0x0020D1B3
            memory[23] = 8'h00;
            memory[22] = 8'h20;
            memory[21] = 8'hD1;
            memory[20] = 8'hB3;

// SLL = 0x0020E1B3

            memory[27] = 8'h00;
            memory[26] = 8'h20;
            memory[25] = 8'hE1;
            memory[24] = 8'hB3;

// SRL = 0x0020F1B3
            memory[31] = 8'h00;
            memory[30] = 8'h20;
            memory[29] = 8'hF1;
            memory[28] = 8'hB3;

// SUB = 0x4020A1B3
            memory[35] = 8'h40;
            memory[34] = 8'h20;
            memory[33] = 8'hA1;
            memory[32] = 8'hB3;

// SRA = 0x4020B1B3
            memory[39] = 8'h40;
            memory[38] = 8'h20;
            memory[37] = 8'hB1;
            memory[36] = 8'hB3;
/////////////////////////Integer R-type///////////////////////////////////////////////////////////////////////////////////////////////////////////////////////

////////////////////////Integer I-type////////////////////////////////////////////////////////////////////////////////////////////////////////////////////////
/*
    In this implementation of I-type we use register x4, and x5 as src and destination respectively
        register mapping:
            x4 = 00100;
            x5 = 00101;
            
            funct3:  ADDI  = 000
                     SLTI  = 001
                     SLTUI = 010
                     ANDI  = 011
                     ORI   = 100
                     XORI  = 101
                     SLLI  = 110
                     SRLI/SRAI  = 111 (depends on the immediate value)
*/
// ADDI = 0x00
            memory[43]
        end
    end
endmodule

instruction_fetch_unit.v
module instruction_fetch_unit (
    input clk,
    input reset,
    input [6:0] opcode,
    input [11:0] imm_address,
    input [11:0] imm_address_jmp,
    input jmp, branch,
    output reg [31:0] pc,
    output reg [31:0] current_pc
);

    // Regular PC increment (4 bytes)
    reg [31:0] next_pc;

    always @(posedge clk or posedge reset) begin
        if (reset) begin
            pc <= 32'b0;
        end else begin
            if (branch) begin
                // If branching, set PC to immediate value
                pc <= {20'b0, imm_address}; // Branch address (adjust according to your system)
            end else begin
                // Otherwise, just increment PC
                next_pc = pc + 4;
                pc <= next_pc;
            end
        end
    end

    always @(posedge clk) begin
        current_pc <= pc;
    end

endmodule

top.v
module top (
    input clk,
    input reset,
    output [31:0] pc_out,
    output [31:0] alu_result
);

    // Wires and registers to connect submodules
    wire [31:0] pc, current_pc, instruction_code;
    wire [11:0] imm_address, imm_address_jmp;
    wire [4:0] rs1, rs2, rd;
    wire [6:0] opcode, funct7;
    wire [2:0] funct3;
    wire [5:0] alu_control;
    wire [31:0] src1, src2, effective_value, write_data_dm;
    wire [31:0] alu_output, data_out_dm;
    reg branch;
    wire beq, bneq, blt, bltu, bge, bgeu, lw, lwi, sw, jmp;

    // Instruction Fetch Unit
    instruction_fetch_unit IFU (
        .clk(clk),
        .reset(reset),
        .opcode(opcode),
        .imm_address(imm_address),
        .imm_address_jmp(imm_address_jmp),
        .jmp(jmp),
        .branch(branch),          // Pass branch signal to IFU
        .pc(pc),
        .current_pc(current_pc)
    );

    // Instruction Memory
    instruction_memory IMEM (
        .clk(clk),
        .reset(reset),
        .pc(pc),
        .instruction_code(instruction_code)
    );

    // Decode instruction fields
    assign opcode = instruction_code[6:0];
    assign funct3 = instruction_code[14:12];
    assign funct7 = instruction_code[31:25];
    assign rs1 = instruction_code[19:15];
    assign rs2 = instruction_code[24:20];
    assign rd = instruction_code[11:7];
    assign imm_address = instruction_code[31:20];
    assign imm_address_jmp = instruction_code[31:20];

    // Control Unit
    control_unit CTRL (
        .reset(reset),
        .funct7(funct7),
        .funct3(funct3),
        .opcode(opcode),
        .alu_control(alu_control),
        .beq(beq),
        .bneq(bneq),
        .blt(blt),
        .bltu(bltu),
        .bge(bge),
        .bgeu(bgeu),
        .lw(lw),
        .lwi(lwi),
        .sw(sw),
        .jmp(jmp)
    );

    // ALU
    alu ALU (
        .rs1(src1),
        .rs2(src2),
        .alu_control(alu_control),
        .imm_val(imm_address), // Immediate value for ALU operations
        .result(alu_output)
    );

    // Register File
    register_file RF (
        .clk(clk),
        .reset(reset),
        .rs1(rs1),
        .rs2(rs2),
        .rd(rd),
        .write_data_dm(write_data_dm),
        .lw(lw),
        .lwi(lwi),
        .jmp(jmp),
        .sw(sw),
        .lw_imm_val(imm_address),
        .return_address(pc),
        .src1(src1),
        .src2(src2),
        .read_data_addr_dm(rd),
        .data_out_dm(data_out_dm),
        .effective_value(effective_value)
    );

    // Output connections
    assign pc_out = pc;
    assign alu_result = alu_output;

    // Branch logic (only deciding whether a branch is taken)
    always @(posedge clk or posedge reset) begin
        if (reset) begin
            branch <= 1'b0; // Clear branch signal on reset
        end else begin
            // Set branch signal based on branch conditions
            branch <= (beq && (src1 == src2)) || 
                      (bneq && (src1 != src2)) || 
                      (blt && ($signed(src1) < $signed(src2))) || 
                      (bltu && (src1 < src2)) || 
                      (bge && ($signed(src1) >= $signed(src2))) || 
                      (bgeu && (src1 >= src2));
        end
    end

endmodule

top_tb.v
module top_tb;
    // Declare signals to connect to the top module
    reg clk;
    reg reset;
    wire [31:0] pc_out;
    wire [31:0] alu_result;

    // Instantiate the top module
    top uut (
        .clk(clk),
        .reset(reset),
        .pc_out(pc_out),
        .alu_result(alu_result)
    );

    // Clock generation
    initial begin
        clk = 0;
        forever #5 clk = ~clk; // 100 MHz clock with 10 ns period
    end

    // Reset and stimulus
    initial begin
        // Dumpfile for GTKWave
        $dumpfile("top_tb.vcd");
        $dumpvars(0, top_tb);

        // Initialize signals
        reset = 1;
        #10;
        reset = 0;

        // Insert additional stimulus here as needed

        #1000; // Run simulation for some time
        $finish;
    end

    // Monitor outputs
    initial begin
        $monitor("Time=%0t | PC Out=%h | ALU Result=%h", $time, pc_out, alu_result);
    end
endmodule

top_tb.vcd
$date
	Thu Nov  7 09:28:01 2024
$end
$version
	Icarus Verilog
$end
$timescale
	1s
$end
$scope module top_tb $end
$var wire 32 ! pc_out [31:0] $end
$var wire 32 " alu_result [31:0] $end
$var reg 1 # clk $end
$var reg 1 $ reset $end
$scope module uut $end
$var wire 32 % alu_result [31:0] $end
$var wire 1 # clk $end
$var wire 32 & pc_out [31:0] $end
$var wire 5 ' rd [4:0] $end
$var wire 1 $ reset $end
$var wire 32 ( write_data_dm [31:0] $end
$var wire 1 ) sw $end
$var wire 32 * src2 [31:0] $end
$var wire 32 + src1 [31:0] $end
$var wire 5 , rs2 [4:0] $end
$var wire 5 - rs1 [4:0] $end
$var wire 32 . pc [31:0] $end
$var wire 7 / opcode [6:0] $end
$var wire 1 0 lwi $end
$var wire 1 1 lw $end
$var wire 1 2 jmp $end
$var wire 32 3 instruction_code [31:0] $end
$var wire 12 4 imm_address_jmp [11:0] $end
$var wire 12 5 imm_address [11:0] $end
$var wire 7 6 funct7 [6:0] $end
$var wire 3 7 funct3 [2:0] $end
$var wire 32 8 effective_value [31:0] $end
$var wire 32 9 data_out_dm [31:0] $end
$var wire 32 : current_pc [31:0] $end
$var wire 1 ; bneq $end
$var wire 1 < bltu $end
$var wire 1 = blt $end
$var wire 1 > bgeu $end
$var wire 1 ? bge $end
$var wire 1 @ beq $end
$var wire 32 A alu_output [31:0] $end
$var wire 6 B alu_control [5:0] $end
$var reg 1 C branch $end
$scope module ALU $end
$var wire 12 D imm_val [11:0] $end
$var wire 32 E rs2 [31:0] $end
$var wire 32 F rs1 [31:0] $end
$var wire 6 G alu_control [5:0] $end
$var reg 32 H result [31:0] $end
$var reg 5 I shft_amnt [4:0] $end
$upscope $end
$scope module CTRL $end
$var wire 3 J funct3 [2:0] $end
$var wire 7 K funct7 [6:0] $end
$var wire 7 L opcode [6:0] $end
$var wire 1 $ reset $end
$var reg 6 M alu_control [5:0] $end
$var reg 1 @ beq $end
$var reg 1 ? bge $end
$var reg 1 > bgeu $end
$var reg 1 = blt $end
$var reg 1 < bltu $end
$var reg 1 ; bneq $end
$var reg 1 2 jmp $end
$var reg 1 1 lw $end
$var reg 1 0 lwi $end
$var reg 1 ) sw $end
$upscope $end
$scope module IFU $end
$var wire 1 C branch $end
$var wire 1 # clk $end
$var wire 12 N imm_address [11:0] $end
$var wire 12 O imm_address_jmp [11:0] $end
$var wire 1 2 jmp $end
$var wire 7 P opcode [6:0] $end
$var wire 1 $ reset $end
$var reg 32 Q current_pc [31:0] $end
$var reg 32 R next_pc [31:0] $end
$var reg 32 S pc [31:0] $end
$upscope $end
$scope module IMEM $end
$var wire 1 # clk $end
$var wire 32 T pc [31:0] $end
$var wire 1 $ reset $end
$var wire 32 U instruction_code [31:0] $end
$upscope $end
$scope module RF $end
$var wire 1 V beq $end
$var wire 1 W bge $end
$var wire 1 X bgeu $end
$var wire 1 Y blt $end
$var wire 1 Z bltu $end
$var wire 1 [ bneq $end
$var wire 1 # clk $end
$var wire 1 2 jmp $end
$var wire 1 1 lw $end
$var wire 12 \ lw_imm_val [11:0] $end
$var wire 1 0 lwi $end
$var wire 5 ] rd [4:0] $end
$var wire 5 ^ read_data_addr_dm [4:0] $end
$var wire 1 $ reset $end
$var wire 32 _ return_address [31:0] $end
$var wire 5 ` rs1 [4:0] $end
$var wire 5 a rs2 [4:0] $end
$var wire 32 b src1 [31:0] $end
$var wire 32 c src2 [31:0] $end
$var wire 1 ) sw $end
$var wire 32 d write_data_dm [31:0] $end
$var wire 32 e effective_value [31:0] $end
$var reg 1 f branch $end
$var reg 32 g data_out_dm [31:0] $end
$var integer 32 h i [31:0] $end
$upscope $end
$upscope $end
$upscope $end
$enddefinitions $end
#0
$dumpvars
b100000 h
b0 g
0f
bx e
bz d
bx c
bx b
bx a
bx `
b0 _
bx ^
bx ]
bx \
z[
zZ
zY
zX
zW
zV
bx U
b0 T
b0 S
bx R
bx Q
bx P
bx O
bx N
b0 M
bx L
bx K
bx J
bx I
bx H
b0 G
bx F
bx E
bx D
0C
b0 B
bx A
x@
x?
x>
x=
x<
x;
bx :
b0 9
bx 8
bx 7
bx 6
bx 5
bx 4
bx 3
x2
x1
x0
bx /
b0 .
bx -
bx ,
bx +
bx *
x)
bz (
bx '
b0 &
bx %
1$
0#
bx "
b0 !
$end
#5
b0 :
b0 Q
b1000 I
b1000 8
b1000 e
b0 "
b0 %
b0 A
b0 H
02
0)
00
01
0>
0?
0<
0=
0;
0@
b1000 4
b1000 O
b1000 5
b1000 D
b1000 N
b1000 \
b0 *
b0 E
b0 c
b1000 ,
b1000 a
b0 +
b0 F
b0 b
b10 -
b10 `
b0 6
b0 K
b0 7
b0 J
b110011 /
b110011 L
b110011 P
b100000010000001010110011 3
b100000010000001010110011 U
b100000 h
1#
#10
0#
0$
#15
b10 B
b10 G
b10 M
b10 7
b10 J
b100000010010001010110011 3
b100000010010001010110011 U
b100 !
b100 &
b100 .
b100 S
b100 T
b100 _
b100 R
1#
#20
0#
#25
b100 B
b100 G
b100 M
b100 7
b100 J
b100000010100001010110011 3
b100000010100001010110011 U
b100 :
b100 Q
b1000 !
b1000 &
b1000 .
b1000 S
b1000 T
b1000 _
b1000 R
1#
#30
0#
#35
b110 B
b110 G
b110 M
b110 7
b110 J
b100000010110001010110011 3
b100000010110001010110011 U
b1000 :
b1000 Q
b1100 !
b1100 &
b1100 .
b1100 S
b1100 T
b1100 _
b1100 R
1#
#40
0#
#45
b0 B
b0 G
b0 M
b11 -
b11 `
b0 7
b0 J
b100000011000001010110011 3
b100000011000001010110011 U
b1100 :
b1100 Q
b10000 !
b10000 &
b10000 .
b10000 S
b10000 T
b10000 _
b10000 R
1#
#50
0#
#55
b10 B
b10 G
b10 M
b10 7
b10 J
b100000011010001010110011 3
b100000011010001010110011 U
b10000 :
b10000 Q
b10100 !
b10100 &
b10100 .
b10100 S
b10100 T
b10100 _
b10100 R
1#
#60
0#
#65
b100 B
b100 G
b100 M
b100 7
b100 J
b100000011100001010110011 3
b100000011100001010110011 U
b10100 :
b10100 Q
b11000 !
b11000 &
b11000 .
b11000 S
b11000 T
b11000 _
b11000 R
1#
#70
0#
#75
b110 B
b110 G
b110 M
b110 7
b110 J
b100000011110001010110011 3
b100000011110001010110011 U
b11000 :
b11000 Q
b11100 !
b11100 &
b11100 .
b11100 S
b11100 T
b11100 _
b11100 R
1#
#80
0#
#85
b100 B
b100 G
b100 M
b10 -
b10 `
b100 7
b100 J
b100000010100001010110011 3
b100000010100001010110011 U
b11100 :
b11100 Q
b100000 !
b100000 &
b100000 .
b100000 S
b100000 T
b100000 _
b100000 R
1#
#90
0#
#95
b110 B
b110 G
b110 M
b110 7
b110 J
b100000010110001010110011 3
b100000010110001010110011 U
b100000 :
b100000 Q
b100100 !
b100100 &
b100100 .
b100100 S
b100100 T
b100100 _
b100100 R
1#
#100
0#
#105
b0 I
b111111 B
b111111 G
b111111 M
b0 4
b0 O
b0 8
b0 e
b0 5
b0 D
b0 N
b0 \
b0 ,
b0 a
b10000 -
b10000 `
b0 7
b0 J
b1001100 /
b1001100 L
b1001100 P
b10000000010011001100 3
b10000000010011001100 U
b100100 :
b100100 Q
b101000 !
b101000 &
b101000 .
b101000 S
b101000 T
b101000 _
b101000 R
1#
#110
0#
#115
b111101 B
b111101 G
b111101 M
b10 7
b10 J
b10000010010011001100 3
b10000010010011001100 U
b101000 :
b101000 Q
b101100 !
b101100 &
b101100 .
b101100 S
b101100 T
b101100 _
b101100 R
1#
#120
0#
#125
b111011 B
b111011 G
b111011 M
b100 7
b100 J
b10000100010011001100 3
b10000100010011001100 U
b101100 :
b101100 Q
b110000 !
b110000 &
b110000 .
b110000 S
b110000 T
b110000 _
b110000 R
1#
#130
0#
#135
b111001 B
b111001 G
b111001 M
b110 7
b110 J
b10000110010011001100 3
b10000110010011001100 U
b110000 :
b110000 Q
b110100 !
b110100 &
b110100 .
b110100 S
b110100 T
b110100 _
b110100 R
1#
#140
0#
#145
b111111 B
b111111 G
b111111 M
b10001 -
b10001 `
b0 7
b0 J
b10001000010011001100 3
b10001000010011001100 U
b110100 :
b110100 Q
b111000 !
b111000 &
b111000 .
b111000 S
b111000 T
b111000 _
b111000 R
1#
#150
0#
#155
b111101 B
b111101 G
b111101 M
b10 7
b10 J
b10001010010011001100 3
b10001010010011001100 U
b111000 :
b111000 Q
b111100 !
b111100 &
b111100 .
b111100 S
b111100 T
b111100 _
b111100 R
1#
#160
0#
#165
b111011 B
b111011 G
b111011 M
b100 7
b100 J
b10001100010011001100 3
b10001100010011001100 U
b111100 :
b111100 Q
b1000000 !
b1000000 &
b1000000 .
b1000000 S
b1000000 T
b1000000 _
b1000000 R
1#
#170
0#
#175
b0 B
b0 G
b0 M
b110 7
b110 J
b1001101 /
b1001101 L
b1001101 P
b10001110010011001101 3
b10001110010011001101 U
b1000000 :
b1000000 Q
b1000100 !
b1000100 &
b1000100 .
b1000100 S
b1000100 T
b1000100 _
b1000100 R
1#
#180
0#
#185
12
b10 -
b10 `
b0 7
b0 J
b1010101 /
b1010101 L
b1010101 P
b10000001001010101 3
b10000001001010101 U
b1000100 :
b1000100 Q
b1001000 !
b1001000 &
b1001000 .
b1001000 S
b1001000 T
b1001000 _
b1001000 R
1#
#190
0#
#195
1;
02
b10 7
b10 J
b10010001001010101 3
b10010001001010101 U
b1001000 :
b1001000 Q
b1001100 !
b1001100 &
b1001100 .
b1001100 S
b1001100 T
b1001100 _
b1001100 R
1#
#200
0#
#205
1<
0;
b100 7
b100 J
b10100001001010101 3
b10100001001010101 U
b1001100 :
b1001100 Q
b1010000 !
b1010000 &
b1010000 .
b1010000 S
b1010000 T
b1010000 _
b1010000 R
1#
#210
0#
#215
1>
0<
b110 7
b110 J
b10110001001010101 3
b10110001001010101 U
b1010000 :
b1010000 Q
b1010100 !
b1010100 &
b1010100 .
b1010100 S
b1010100 T
b1010100 _
b1010100 R
1#
#220
0#
#225
12
0>
b11 -
b11 `
b0 7
b0 J
b11000001001010101 3
b11000001001010101 U
b1010100 :
b1010100 Q
1C
b1011000 !
b1011000 &
b1011000 .
b1011000 S
b1011000 T
b1011000 _
b1011000 R
1#
#230
0#
#235
b1000 I
02
b1000 4
b1000 O
b1000 8
b1000 e
b1000 5
b1000 D
b1000 N
b1000 \
b1000 ,
b1000 a
b10 -
b10 `
b110011 /
b110011 L
b110011 P
b100000010000001010110011 3
b100000010000001010110011 U
b1011000 :
b1011000 Q
b0 !
b0 &
b0 .
b0 S
b0 T
b0 _
0C
1#
#240
0#
#245
b10 B
b10 G
b10 M
b10 7
b10 J
b100000010010001010110011 3
b100000010010001010110011 U
b0 :
b0 Q
b100 !
b100 &
b100 .
b100 S
b100 T
b100 _
b100 R
1#
#250
0#
#255
b100 B
b100 G
b100 M
b100 7
b100 J
b100000010100001010110011 3
b100000010100001010110011 U
b100 :
b100 Q
b1000 !
b1000 &
b1000 .
b1000 S
b1000 T
b1000 _
b1000 R
1#
#260
0#
#265
b110 B
b110 G
b110 M
b110 7
b110 J
b100000010110001010110011 3
b100000010110001010110011 U
b1000 :
b1000 Q
b1100 !
b1100 &
b1100 .
b1100 S
b1100 T
b1100 _
b1100 R
1#
#270
0#
#275
b0 B
b0 G
b0 M
b11 -
b11 `
b0 7
b0 J
b100000011000001010110011 3
b100000011000001010110011 U
b1100 :
b1100 Q
b10000 !
b10000 &
b10000 .
b10000 S
b10000 T
b10000 _
b10000 R
1#
#280
0#
#285
b10 B
b10 G
b10 M
b10 7
b10 J
b100000011010001010110011 3
b100000011010001010110011 U
b10000 :
b10000 Q
b10100 !
b10100 &
b10100 .
b10100 S
b10100 T
b10100 _
b10100 R
1#
#290
0#
#295
b100 B
b100 G
b100 M
b100 7
b100 J
b100000011100001010110011 3
b100000011100001010110011 U
b10100 :
b10100 Q
b11000 !
b11000 &
b11000 .
b11000 S
b11000 T
b11000 _
b11000 R
1#
#300
0#
#305
b110 B
b110 G
b110 M
b110 7
b110 J
b100000011110001010110011 3
b100000011110001010110011 U
b11000 :
b11000 Q
b11100 !
b11100 &
b11100 .
b11100 S
b11100 T
b11100 _
b11100 R
1#
#310
0#
#315
b100 B
b100 G
b100 M
b10 -
b10 `
b100 7
b100 J
b100000010100001010110011 3
b100000010100001010110011 U
b11100 :
b11100 Q
b100000 !
b100000 &
b100000 .
b100000 S
b100000 T
b100000 _
b100000 R
1#
#320
0#
#325
b110 B
b110 G
b110 M
b110 7
b110 J
b100000010110001010110011 3
b100000010110001010110011 U
b100000 :
b100000 Q
b100100 !
b100100 &
b100100 .
b100100 S
b100100 T
b100100 _
b100100 R
1#
#330
0#
#335
b0 I
b111111 B
b111111 G
b111111 M
b0 4
b0 O
b0 8
b0 e
b0 5
b0 D
b0 N
b0 \
b0 ,
b0 a
b10000 -
b10000 `
b0 7
b0 J
b1001100 /
b1001100 L
b1001100 P
b10000000010011001100 3
b10000000010011001100 U
b100100 :
b100100 Q
b101000 !
b101000 &
b101000 .
b101000 S
b101000 T
b101000 _
b101000 R
1#
#340
0#
#345
b111101 B
b111101 G
b111101 M
b10 7
b10 J
b10000010010011001100 3
b10000010010011001100 U
b101000 :
b101000 Q
b101100 !
b101100 &
b101100 .
b101100 S
b101100 T
b101100 _
b101100 R
1#
#350
0#
#355
b111011 B
b111011 G
b111011 M
b100 7
b100 J
b10000100010011001100 3
b10000100010011001100 U
b101100 :
b101100 Q
b110000 !
b110000 &
b110000 .
b110000 S
b110000 T
b110000 _
b110000 R
1#
#360
0#
#365
b111001 B
b111001 G
b111001 M
b110 7
b110 J
b10000110010011001100 3
b10000110010011001100 U
b110000 :
b110000 Q
b110100 !
b110100 &
b110100 .
b110100 S
b110100 T
b110100 _
b110100 R
1#
#370
0#
#375
b111111 B
b111111 G
b111111 M
b10001 -
b10001 `
b0 7
b0 J
b10001000010011001100 3
b10001000010011001100 U
b110100 :
b110100 Q
b111000 !
b111000 &
b111000 .
b111000 S
b111000 T
b111000 _
b111000 R
1#
#380
0#
#385
b111101 B
b111101 G
b111101 M
b10 7
b10 J
b10001010010011001100 3
b10001010010011001100 U
b111000 :
b111000 Q
b111100 !
b111100 &
b111100 .
b111100 S
b111100 T
b111100 _
b111100 R
1#
#390
0#
#395
b111011 B
b111011 G
b111011 M
b100 7
b100 J
b10001100010011001100 3
b10001100010011001100 U
b111100 :
b111100 Q
b1000000 !
b1000000 &
b1000000 .
b1000000 S
b1000000 T
b1000000 _
b1000000 R
1#
#400
0#
#405
b0 B
b0 G
b0 M
b110 7
b110 J
b1001101 /
b1001101 L
b1001101 P
b10001110010011001101 3
b10001110010011001101 U
b1000000 :
b1000000 Q
b1000100 !
b1000100 &
b1000100 .
b1000100 S
b1000100 T
b1000100 _
b1000100 R
1#
#410
0#
#415
12
b10 -
b10 `
b0 7
b0 J
b1010101 /
b1010101 L
b1010101 P
b10000001001010101 3
b10000001001010101 U
b1000100 :
b1000100 Q
b1001000 !
b1001000 &
b1001000 .
b1001000 S
b1001000 T
b1001000 _
b1001000 R
1#
#420
0#
#425
1;
02
b10 7
b10 J
b10010001001010101 3
b10010001001010101 U
b1001000 :
b1001000 Q
b1001100 !
b1001100 &
b1001100 .
b1001100 S
b1001100 T
b1001100 _
b1001100 R
1#
#430
0#
#435
1<
0;
b100 7
b100 J
b10100001001010101 3
b10100001001010101 U
b1001100 :
b1001100 Q
b1010000 !
b1010000 &
b1010000 .
b1010000 S
b1010000 T
b1010000 _
b1010000 R
1#
#440
0#
#445
1>
0<
b110 7
b110 J
b10110001001010101 3
b10110001001010101 U
b1010000 :
b1010000 Q
b1010100 !
b1010100 &
b1010100 .
b1010100 S
b1010100 T
b1010100 _
b1010100 R
1#
#450
0#
#455
12
0>
b11 -
b11 `
b0 7
b0 J
b11000001001010101 3
b11000001001010101 U
b1010100 :
b1010100 Q
b1011000 !
b1011000 &
b1011000 .
b1011000 S
b1011000 T
b1011000 _
1C
b1011000 R
1#
#460
0#
#465
b1000 I
02
b1000 4
b1000 O
b1000 8
b1000 e
b1000 5
b1000 D
b1000 N
b1000 \
b1000 ,
b1000 a
b10 -
b10 `
b110011 /
b110011 L
b110011 P
b100000010000001010110011 3
b100000010000001010110011 U
b1011000 :
b1011000 Q
0C
b0 !
b0 &
b0 .
b0 S
b0 T
b0 _
1#
#470
0#
#475
b10 B
b10 G
b10 M
b10 7
b10 J
b100000010010001010110011 3
b100000010010001010110011 U
b0 :
b0 Q
b100 !
b100 &
b100 .
b100 S
b100 T
b100 _
b100 R
1#
#480
0#
#485
b100 B
b100 G
b100 M
b100 7
b100 J
b100000010100001010110011 3
b100000010100001010110011 U
b100 :
b100 Q
b1000 !
b1000 &
b1000 .
b1000 S
b1000 T
b1000 _
b1000 R
1#
#490
0#
