register_file.v
module register_file (
    input clk, reset,
    input [4:0] rs1, rs2, rd,
    input [31:0] write_data_dm, // Data coming from memory
    input lw, lwi, jmp, sw,
    input [11:0] lw_imm_val, // Immediate offset for load word
    input [31:0] return_address,
    input beq, bneq, blt, bltu, bge, bgeu,

    output [31:0] src1, src2,
    output [4:0] read_data_addr_dm,
    output reg [31:0] data_out_dm,
    output [31:0] effective_value // Effective address output for memory
);
    reg [31:0] reg_mem[31:0];
    integer i;
    reg branch;

    assign read_data_addr_dm = rd;
    assign effective_value = reg_mem[rs1] + {{20{lw_imm_val[11]}}, lw_imm_val}; // Sign-extend lw_imm_val to 32 bits

    always @(posedge clk or posedge reset) begin
        if (reset) begin
            // Initialize all registers to 0
            for (i = 0; i < 32; i = i + 1) begin
                reg_mem[i] <= 32'b0;
            end
            data_out_dm <= 32'b0; // Reset data_out_dm
            branch <= 1'b0;
        end else begin
            // Load Word
            if (lw) begin
                reg_mem[rd] <= write_data_dm; // Load from memory to register
            end

            // Store Word
            if (sw) begin
                data_out_dm <= reg_mem[rs1]; // Store the value in src1 to data_out_dm
            end 

            // Load Immediate
            if (lwi) begin
                reg_mem[rd] <= effective_value; // Load immediate address directly
            end 

            // Jump Operation
            if (jmp) begin
                reg_mem[rd] <= return_address; // Store the jump return address in rd
            end
        end
    end

    // Combinational read for rs1 and rs2
    assign src1 = reg_mem[rs1];
    assign src2 = reg_mem[rs2];

endmodule

alu.v
module alu (
    input [31:0] rs1,
    input [31:0] rs2,
    input [5:0] alu_control,
    input [11:0] imm_val,
    output reg [31:0] result
);
    reg [4:0] shft_amnt;

    always @(*) begin
        shft_amnt = imm_val[4:0];
    end

    always @(*) begin
        case (alu_control)
            6'b000000: begin
                result = rs1 + rs2; // ADD operation
            end
            6'b000001: begin
                result = ($signed(rs1) < $signed(rs2)) ? 1 : 0; // SLT (signed comparison)
            end 
            6'b000010: begin
                result = (rs1 < rs2) ? 1 : 0; // SLTU (unsigned comparison)
            end
            6'b000011: begin
                result = rs1 & rs2; // AND
            end
            6'b000100: begin
                result = rs1 | rs2; // OR
            end
            6'b000101: begin
                result = rs1 ^ rs2; // XOR
            end
            6'b000110: begin
                result = rs1 << shft_amnt; // SLL (shift left logical)
            end
            6'b000111: begin
                result = rs1 >> shft_amnt; // SRL (shift right logical)
            end
            6'b001000: begin
                result = rs1 - rs2; // SUB
            end
            6'b001001: begin
                result = rs1 >>> shft_amnt; // SRA (shift right arithmetic)
            end
            6'b111111: begin
                result = rs1 + imm_val; // ADDI
            end
            6'b111110: begin
                result = ($signed(rs1) < $signed(imm_val)) ? 1 : 0; // SLTI
            end
            6'b111101: begin
                result = (rs1 < imm_val) ? 1 : 0; // SLTIU
            end
            6'b111100: begin
                result = rs1 & imm_val; // ANDI
            end
            6'b111011: begin
                result = rs1 | imm_val; // ORI
            end
            6'b111010: begin
                result = rs1 ^ imm_val; // XORI
            end
            6'b111000: begin
                if (imm_val[11:5] == 7'b0000000) begin
                    result = rs1 >> shft_amnt; // SRLI
                end else if (imm_val[11:5] == 7'b0100000) begin
                    result = rs1 >>> shft_amnt; // SRAI
                end else begin
                    result = 32'b0; // Default to 0 if imm_val doesn't match
                end
            end
            default: result = 32'b0; // Default case
        endcase
    end
    
endmodule

control_unit.v
module control_unit (
    input reset,
    input [6:0] funct7,
    input [2:0] funct3,
    input [6:0] opcode,

    output reg [5:0] alu_control, // ALU control signal
    output reg beq, bneq, blt, bltu, bge, bgeu, // Branch control signals
    output reg lw, lwi, sw, // Load and Store signals
    output reg jmp // Jump signal
);

    // Parameters for instruction types
    parameter R_type = 7'b0110011;
    parameter I_type = 7'b1001100;
    parameter Control_Transfer_Load_Store = 7'b1010101;

    // Reset handling for ALU control signal
    always @(posedge reset) begin
        if (reset)
            alu_control = 6'b000000;
    end

    // Main control logic
    always @(*) begin
        // Default control signal values
        alu_control = 6'b000000;
        beq = 0;
        bneq = 0;
        blt = 0;
        bltu = 0;
        bge = 0;
        bgeu = 0;
        lw = 0;
        lwi = 0;
        sw = 0;
        jmp = 0;

        case (opcode)
            // R-type operations
            R_type: begin
                case (funct7)
                    7'b0000000: begin
                        case (funct3)
                            3'b000: alu_control = 6'b000000; // ADD
                            3'b001: alu_control = 6'b000001; // SLT
                            3'b010: alu_control = 6'b000010; // SLTU
                            3'b011: alu_control = 6'b000011; // AND
                            3'b100: alu_control = 6'b000100; // OR
                            3'b101: alu_control = 6'b000101; // XOR
                            3'b110: alu_control = 6'b000110; // SLL
                            3'b111: alu_control = 6'b000111; // SRL
                            default: ;
                        endcase
                    end
                    7'b0100000: begin
                        case (funct3)
                            3'b010: alu_control = 6'b001000; // SUB
                            3'b011: alu_control = 6'b001001; // SRA
                            default: ;
                        endcase
                    end
                    default: ;
                endcase
            end

            // I-type operations
            I_type: begin
                case (funct3)
                    3'b000: alu_control = 6'b111111; // ADDI
                    3'b001: alu_control = 6'b111110; // SLTI
                    3'b010: alu_control = 6'b111101; // SLTUI
                    3'b011: alu_control = 6'b111100; // ANDI
                    3'b100: alu_control = 6'b111011; // ORI
                    3'b101: alu_control = 6'b111010; // XORI
                    3'b110: alu_control = 6'b111001; // SLLI
                    3'b111: alu_control = 6'b111000; // SRLI or SRAI
                    default: ;
                endcase
            end

            // Control Transfer, Load, and Store operations
            Control_Transfer_Load_Store: begin
                case (funct3)
                    3'b000: jmp = 1'b1;       // Jump
                    3'b001: beq = 1'b1;       // BEQ
                    3'b010: bneq = 1'b1;      // BNEQ
                    3'b011: blt = 1'b1;       // BLT
                    3'b100: bltu = 1'b1;      // BLTU
                    3'b101: bge = 1'b1;       // BGE
                    3'b110: bgeu = 1'b1;      // BGEU
                    3'b111: begin
                        case (funct7)
                            7'b1111111: lwi = 1'b1; // Load Word Immediate
                            7'b0001000: sw = 1'b1;  // Store Word
                            7'b0000000: lw = 1'b1;  // Load Word
                            default: ;
                        endcase
                    end
                    default: ;
                endcase
            end
            
            default: ;
        endcase
    end
endmodule

instruction_memory.v
module instruction_memory (
    input clk, reset,
    input [31:0] pc,

    output [31:0] instruction_code
);
    reg [8:0] memory [111:0]; 
    assign instruction_code = {memory[pc+3], memory[pc+2], memory[pc+1], memory[pc]};

    always @(posedge clk ) begin
        if (reset) begin
//////////////////////////////////////////////////////Integer R-Type Instructions//////////////////////////////////////////////////////////
/*  In this implementation of RISC-V in the given code, integer register operations are carried out by x1, x2, and x3 registers
    where operands for operation are x1 and x2 and destination to store the result is x3.
            register mapping x1 = 5'b00001
                             x2 = 5'b00010
                             x3 = 5'b00011
            funct3:  ADD  = 000
                     SLT  = 001
                     SLTU = 010
                     AND  = 011
                     OR   = 100
                     XOR  = 101
                     SLL  = 110
                     SRL  = 111
Hence the instruction becomes  (0000 000)(0 0010) (0000 1)(000 - 111) (0001 1)(011 0011) -> (funct7)(src2)(src1)(funct3)(rd)(opcode)

Similarly for the R-type instruction SUB and SLA
funct7 = 0100 000 and 
           funct3:   SUB  = 010
                     SLA  = 011
Hence the instruction becomes  (0100 000)(0 0010) (0000 1)(000 - 111) (0001 1)(011 0011) -> (funct7)(src2)(src1)(funct3)(rd)(opcode)
*/
              
// ADD = 0x002081B3 
           memory[3] = 8'h00;
           memory[2] = 8'h20;
           memory[1] = 8'h81;
           memory[0] = 8'hB3;

//  SLT = 0x002091B3        
            memory[7] = 8'h00;
            memory[6] = 8'h20;
            memory[5] = 8'h91;
            memory[4] = 8'hB3;

// SLTU = 0x0020A1B3
            memory[11] = 8'h00;
            memory[10] = 8'h20;
            memory[9] = 8'hA1;
            memory[8] = 8'hB3;

// AND = 0x0020B1B3
            memory[15] = 8'h00;
            memory[14] = 8'h20;
            memory[13] = 8'hB1;
            memory[12] = 8'hB3;

// OR = 0x0020C1B3
            memory[19] = 8'h00;
            memory[18] = 8'h20;
            memory[17] = 8'hC1;
            memory[16] = 8'hB3;

// XOR = 0x0020D1B3
            memory[23] = 8'h00;
            memory[22] = 8'h20;
            memory[21] = 8'hD1;
            memory[20] = 8'hB3;

// SLL = 0x0020E1B3

            memory[27] = 8'h00;
            memory[26] = 8'h20;
            memory[25] = 8'hE1;
            memory[24] = 8'hB3;

// SRL = 0x0020F1B3
            memory[31] = 8'h00;
            memory[30] = 8'h20;
            memory[29] = 8'hF1;
            memory[28] = 8'hB3;

// SUB = 0x4020A1B3
            memory[35] = 8'h40;
            memory[34] = 8'h20;
            memory[33] = 8'hA1;
            memory[32] = 8'hB3;

// SRA = 0x4020B1B3
            memory[39] = 8'h40;
            memory[38] = 8'h20;
            memory[37] = 8'hB1;
            memory[36] = 8'hB3;
/////////////////////////Integer R-type///////////////////////////////////////////////////////////////////////////////////////////////////////////////////////

////////////////////////Integer I-type////////////////////////////////////////////////////////////////////////////////////////////////////////////////////////
/*
    In this implementation of I-type we use register x4, and x5 as src and destination respectively
        register mapping:
            x4 = 00100;
            x5 = 00101;
            
            funct3:  ADDI  = 000
                     SLTI  = 001
                     SLTUI = 010
                     ANDI  = 011
                     ORI   = 100
                     XORI  = 101
                     SLLI  = 110
                     SRLI/SRAI  = 111 (depends on the immediate value)
*/
// ADDI = 0x000202CC
            memory[43] = 8'h00;
            memory[42] = 8'h02;
            memory[41] = 8'h02;
            memory[40] = 8'hCC;

// SLTI = 0x000212CC
            memory[47] = 8'h00;
            memory[46] = 8'h02;
            memory[45] = 8'h12;
            memory[44] = 8'hCC;
// SLTUI = 0x000222CC 
            memory[51] = 8'h00;
            memory[50] = 8'h02;
            memory[49] = 8'h22;
            memory[48] = 8'hCC;
// ANDI = 0x000232CC
            memory[55] = 8'h00;
            memory[54] = 8'h02;
            memory[53] = 8'h32;
            memory[52] = 8'hCC;
// ORI = 0x000242CC
            memory[59] = 8'h00;
            memory[58] = 8'h02;
            memory[57] = 8'h42;
            memory[56] = 8'hCC;
// XORI = 0x000252CC
            memory[63] = 8'h00;
            memory[62] = 8'h02;
            memory[61] = 8'h52;
            memory[60] = 8'hCC;
// SLLI = 0x000262CC
            memory[67] = 8'h00;
            memory[66] = 8'h02;
            memory[65] = 8'h62;
            memory[64] = 8'hCC;
// SRLI = 0x000272CC
            memory[71] = 8'h00;
            memory[70] = 8'h02;
            memory[69] = 8'h72;
            memory[68] = 8'hCC;
// SRAI = 0x000272CD
            memory[71] = 8'h00;
            memory[70] = 8'h02;
            memory[69] = 8'h72;
            memory[68] = 8'hCD;
//////////////////////////Control Transfer and Load Instructions//////////////
// JALR = 0x002080C5
            memory[75] = 8'h00;
            memory[74] = 8'h00;
            memory[73] = 8'h81;
            memory[72] = 8'h55;
// BEQ = 0x00009155
            memory[79] = 8'h00;
            memory[78] = 8'h00;
            memory[77] = 8'h91;
            memory[76] = 8'h55;
// BNEQ = 0x0000A155
            memory[83] = 8'h00;
            memory[82] = 8'h00;
            memory[81] = 8'hA1;
            memory[80] = 8'h55;
// BLT = 0x0000B155
            memory[87] = 8'h00;
            memory[86] = 8'h00;
            memory[85] = 8'hB1;
            memory[84] = 8'h55;
// BLTU = 0x0000C155
            memory[91] = 8'h00;
            memory[90] = 8'h00;
            memory[89] = 8'hC1;
            memory[88] = 8'h55;
// BGE = 0x0000D155
            memory[95] = 8'h00;
            memory[94] = 8'h00;
            memory[93] = 8'hD1;
            memory[92] = 8'h55;
// BGEU = 0x0000E155
            memory[99] = 8'h00;
            memory[98] = 8'h00;
            memory[97] = 8'hE1;
            memory[96] = 8'h55;
// LW = 0x0000F155
            memory[103] = 8'h00;
            memory[102] = 8'h00;
            memory[101] = 8'hF1;
            memory[100] = 8'h55;
// LWI = 0xFF00F155
            memory[107] = 8'hFF;
            memory[106] = 8'h00;
            memory[105] = 8'hF1;
            memory[104] = 8'h55;
// SW = 0x1000F155
            memory[111] = 8'h10;
            memory[110] = 8'h00;
            memory[109] = 8'hF1;
            memory[108] = 8'h55;
        end
    end
endmodule

instruction_fetch_unit.v
module instruction_fetch_unit (
    input clk,
    input reset,
    input [6:0] opcode,
    input [11:0] imm_address,
    input [11:0] imm_address_jmp,
    input jmp, branch,
    output reg [31:0] pc,
    output reg [31:0] current_pc
);

    // Regular PC increment (4 bytes)
    reg [31:0] next_pc;

    always @(posedge clk or posedge reset) begin
        if (reset) begin
            pc <= 32'b0;
        end else begin
            if (branch) begin
                // If branching, set PC to immediate value
                pc <= {20'b0, imm_address}; // Branch address (adjust according to your system)
            end else begin
                // Otherwise, just increment PC
                next_pc = pc + 4;
                pc <= next_pc;
            end
        end
    end

    always @(posedge clk) begin
        current_pc <= pc;
    end

endmodule

top.v
module top (
    input clk,
    input reset,
    output [31:0] pc_out,
    output [31:0] alu_result
);

    // Wires and registers to connect submodules
    wire [31:0] pc, current_pc, instruction_code;
    wire [11:0] imm_address, imm_address_jmp;
    wire [4:0] rs1, rs2, rd;
    wire [6:0] opcode, funct7;
    wire [2:0] funct3;
    wire [5:0] alu_control;
    wire [31:0] src1, src2, effective_value, write_data_dm;
    wire [31:0] alu_output, data_out_dm;
    reg branch;
    wire beq, bneq, blt, bltu, bge, bgeu, lw, lwi, sw, jmp;

    // Instruction Fetch Unit
    instruction_fetch_unit IFU (
        .clk(clk),
        .reset(reset),
        .opcode(opcode),
        .imm_address(imm_address),
        .imm_address_jmp(imm_address_jmp),
        .jmp(jmp),
        .branch(branch),          // Pass branch signal to IFU
        .pc(pc),
        .current_pc(current_pc)
    );

    // Instruction Memory
    instruction_memory IMEM (
        .clk(clk),
        .reset(reset),
        .pc(pc),
        .instruction_code(instruction_code)
    );

    // Decode instruction fields
    assign opcode = instruction_code[6:0];
    assign funct3 = instruction_code[14:12];
    assign funct7 = instruction_code[31:25];
    assign rs1 = instruction_code[19:15];
    assign rs2 = instruction_code[24:20];
    assign rd = instruction_code[11:7];
    assign imm_address = instruction_code[31:20];
    assign imm_address_jmp = instruction_code[31:20];

    // Control Unit
    control_unit CTRL (
        .reset(reset),
        .funct7(funct7),
        .funct3(funct3),
        .opcode(opcode),
        .alu_control(alu_control),
        .beq(beq),
        .bneq(bneq),
        .blt(blt),
        .bltu(bltu),
        .bge(bge),
        .bgeu(bgeu),
        .lw(lw),
        .lwi(lwi),
        .sw(sw),
        .jmp(jmp)
    );

    // ALU
    alu ALU (
        .rs1(src1),
        .rs2(src2),
        .alu_control(alu_control),
        .imm_val(imm_address), // Immediate value for ALU operations
        .result(alu_output)
    );

    // Register File
    register_file RF (
        .clk(clk),
        .reset(reset),
        .rs1(rs1),
        .rs2(rs2),
        .rd(rd),
        .write_data_dm(write_data_dm),
        .lw(lw),
        .lwi(lwi),
        .jmp(jmp),
        .sw(sw),
        .lw_imm_val(imm_address),
        .return_address(pc),
        .src1(src1),
        .src2(src2),
        .read_data_addr_dm(rd),
        .data_out_dm(data_out_dm),
        .effective_value(effective_value)
    );

    // Output connections
    assign pc_out = pc;
    assign alu_result = alu_output;

    // Branch logic (only deciding whether a branch is taken)
    always @(posedge clk or posedge reset) begin
        if (reset) begin
            branch <= 1'b0; // Clear branch signal on reset
        end else begin
            // Set branch signal based on branch conditions
            branch <= (beq && (src1 == src2)) || 
                      (bneq && (src1 != src2)) || 
                      (blt && ($signed(src1) < $signed(src2))) || 
                      (bltu && (src1 < src2)) || 
                      (bge && ($signed(src1) >= $signed(src2))) || 
                      (bgeu && (src1 >= src2));
        end
    end

endmodule

top_tb.v
`timescale 1ns / 1ps

module top_tb;
    // Declare signals to connect to the top module
    reg clk;
    reg reset;
    wire [31:0] pc_out;
    wire [31:0] alu_result;

    // Instantiate the top module
    top uut (
        .clk(clk),
        .reset(reset),
        .pc_out(pc_out),
        .alu_result(alu_result)
    );

    // Clock generation
    initial begin
        clk = 0;
        forever #5 clk = ~clk; // 100 MHz clock with 10 ns period
    end

    // Reset and stimulus
    initial begin
        // Dumpfile for GTKWave
        $dumpfile("top_tb.vcd");
        $dumpvars(0, top_tb);

        // Initialize signals
        reset = 1;
        #10;
        reset = 0;

        // Insert additional stimulus here as needed

        #1000; // Run simulation for some time
        $finish;
    end

    // Monitor outputs
    initial begin
        $monitor("Time=%0t | PC Out=%h | ALU Result=%h", $time, pc_out, alu_result);
    end
endmodule

top_tb.vcd
$date
	Thu Nov  7 09:21:25 2024
$end
$version
	Icarus Verilog
$end
$timescale
	1ps
$end
$scope module top_tb $end
$var wire 32 ! pc_out [31:0] $end
$var wire 32 " alu_result [31:0] $end
$var reg 1 # clk $end
$var reg 1 $ reset $end
$scope module uut $end
$var wire 32 % alu_result [31:0] $end
$var wire 1 # clk $end
$var wire 32 & pc_out [31:0] $end
$var wire 5 ' rd [4:0] $end
$var wire 1 $ reset $end
$var wire 32 ( write_data_dm [31:0] $end
$var wire 1 ) sw $end
$var wire 32 * src2 [31:0] $end
$var wire 32 + src1 [31:0] $end
$var wire 5 , rs2 [4:0] $end
$var wire 5 - rs1 [4:0] $end
$var wire 32 . pc [31:0] $end
$var wire 7 / opcode [6:0] $end
$var wire 1 0 lwi $end
$var wire 1 1 lw $end
$var wire 1 2 jmp $end
$var wire 32 3 instruction_code [31:0] $end
$var wire 12 4 imm_address_jmp [11:0] $end
$var wire 12 5 imm_address [11:0] $end
$var wire 7 6 funct7 [6:0] $end
$var wire 3 7 funct3 [2:0] $end
$var wire 32 8 effective_value [31:0] $end
$var wire 32 9 data_out_dm [31:0] $end
$var wire 32 : current_pc [31:0] $end
$var wire 1 ; bneq $end
$var wire 1 < bltu $end
$var wire 1 = blt $end
$var wire 1 > bgeu $end
$var wire 1 ? bge $end
$var wire 1 @ beq $end
$var wire 32 A alu_output [31:0] $end
$var wire 6 B alu_control [5:0] $end
$var reg 1 C branch $end
$scope module ALU $end
$var wire 12 D imm_val [11:0] $end
$var wire 32 E rs2 [31:0] $end
$var wire 32 F rs1 [31:0] $end
$var wire 6 G alu_control [5:0] $end
$var reg 32 H result [31:0] $end
$var reg 5 I shft_amnt [4:0] $end
$upscope $end
$scope module CTRL $end
$var wire 3 J funct3 [2:0] $end
$var wire 7 K funct7 [6:0] $end
$var wire 7 L opcode [6:0] $end
$var wire 1 $ reset $end
$var reg 6 M alu_control [5:0] $end
$var reg 1 @ beq $end
$var reg 1 ? bge $end
$var reg 1 > bgeu $end
$var reg 1 = blt $end
$var reg 1 < bltu $end
$var reg 1 ; bneq $end
$var reg 1 2 jmp $end
$var reg 1 1 lw $end
$var reg 1 0 lwi $end
$var reg 1 ) sw $end
$upscope $end
$scope module IFU $end
$var wire 1 C branch $end
$var wire 1 # clk $end
$var wire 12 N imm_address [11:0] $end
$var wire 12 O imm_address_jmp [11:0] $end
$var wire 1 2 jmp $end
$var wire 7 P opcode [6:0] $end
$var wire 1 $ reset $end
$var reg 32 Q current_pc [31:0] $end
$var reg 32 R next_pc [31:0] $end
$var reg 32 S pc [31:0] $end
$upscope $end
$scope module IMEM $end
$var wire 1 # clk $end
$var wire 32 T pc [31:0] $end
$var wire 1 $ reset $end
$var wire 32 U instruction_code [31:0] $end
$upscope $end
$scope module RF $end
$var wire 1 V beq $end
$var wire 1 W bge $end
$var wire 1 X bgeu $end
$var wire 1 Y blt $end
$var wire 1 Z bltu $end
$var wire 1 [ bneq $end
$var wire 1 # clk $end
$var wire 1 2 jmp $end
$var wire 1 1 lw $end
$var wire 12 \ lw_imm_val [11:0] $end
$var wire 1 0 lwi $end
$var wire 5 ] rd [4:0] $end
$var wire 5 ^ read_data_addr_dm [4:0] $end
$var wire 1 $ reset $end
$var wire 32 _ return_address [31:0] $end
$var wire 5 ` rs1 [4:0] $end
$var wire 5 a rs2 [4:0] $end
$var wire 32 b src1 [31:0] $end
$var wire 32 c src2 [31:0] $end
$var wire 1 ) sw $end
$var wire 32 d write_data_dm [31:0] $end
$var wire 32 e effective_value [31:0] $end
$var reg 1 f branch $end
$var reg 32 g data_out_dm [31:0] $end
$var integer 32 h i [31:0] $end
$upscope $end
$upscope $end
$upscope $end
$enddefinitions $end
#0
$dumpvars
b100000 h
b0 g
0f
bx e
bz d
bx c
bx b
bx a
bx `
b0 _
bx ^
bx ]
bx \
z[
zZ
zY
zX
zW
zV
bx U
b0 T
b0 S
bx R
bx Q
bx P
bx O
bx N
b0 M
bx L
bx K
bx J
bx I
bx H
b0 G
bx F
bx E
bx D
0C
b0 B
bx A
x@
x?
x>
x=
x<
x;
bx :
b0 9
bx 8
bx 7
bx 6
bx 5
bx 4
bx 3
x2
x1
x0
bx /
b0 .
bx -
bx ,
bx +
bx *
x)
bz (
bx '
b0 &
bx %
1$
0#
bx "
b0 !
$end
#5000
b0 :
b0 Q
b1000 I
b1000 8
b1000 e
b0 "
b0 %
b0 A
b0 H
02
0)
00
01
0>
0?
0<
0=
0;
0@
b1000 4
b1000 O
b1000 5
b1000 D
b1000 N
b1000 \
b0 *
b0 E
b0 c
b1000 ,
b1000 a
b0 +
b0 F
b0 b
b10 -
b10 `
b0 6
b0 K
b0 7
b0 J
b110011 /
b110011 L
b110011 P
b100000010000001010110011 3
b100000010000001010110011 U
b100000 h
1#
#10000
0#
0$
#15000
b10 B
b10 G
b10 M
b10 7
b10 J
b100000010010001010110011 3
b100000010010001010110011 U
b100 !
b100 &
b100 .
b100 S
b100 T
b100 _
b100 R
1#
#20000
0#
#25000
b100 B
b100 G
b100 M
b100 7
b100 J
b100000010100001010110011 3
b100000010100001010110011 U
b100 :
b100 Q
b1000 !
b1000 &
b1000 .
b1000 S
b1000 T
b1000 _
b1000 R
1#
#30000
0#
#35000
b110 B
b110 G
b110 M
b110 7
b110 J
b100000010110001010110011 3
b100000010110001010110011 U
b1000 :
b1000 Q
b1100 !
b1100 &
b1100 .
b1100 S
b1100 T
b1100 _
b1100 R
1#
#40000
0#
#45000
b0 B
b0 G
b0 M
b11 -
b11 `
b0 7
b0 J
b100000011000001010110011 3
b100000011000001010110011 U
b1100 :
b1100 Q
b10000 !
b10000 &
b10000 .
b10000 S
b10000 T
b10000 _
b10000 R
1#
#50000
0#
#55000
b10 B
b10 G
b10 M
b10 7
b10 J
b100000011010001010110011 3
b100000011010001010110011 U
b10000 :
b10000 Q
b10100 !
b10100 &
b10100 .
b10100 S
b10100 T
b10100 _
b10100 R
1#
#60000
0#
#65000
b100 B
b100 G
b100 M
b100 7
b100 J
b100000011100001010110011 3
b100000011100001010110011 U
b10100 :
b10100 Q
b11000 !
b11000 &
b11000 .
b11000 S
b11000 T
b11000 _
b11000 R
1#
#70000
0#
#75000
b110 B
b110 G
b110 M
b110 7
b110 J
b100000011110001010110011 3
b100000011110001010110011 U
b11000 :
b11000 Q
b11100 !
b11100 &
b11100 .
b11100 S
b11100 T
b11100 _
b11100 R
1#
#80000
0#
#85000
b100 B
b100 G
b100 M
b10 -
b10 `
b100 7
b100 J
b100000010100001010110011 3
b100000010100001010110011 U
b11100 :
b11100 Q
b100000 !
b100000 &
b100000 .
b100000 S
b100000 T
b100000 _
b100000 R
1#
#90000
0#
#95000
b110 B
b110 G
b110 M
b110 7
b110 J
b100000010110001010110011 3
b100000010110001010110011 U
b100000 :
b100000 Q
b100100 !
b100100 &
b100100 .
b100100 S
b100100 T
b100100 _
b100100 R
1#
#100000
0#
#105000
b0 I
b111111 B
b111111 G
b111111 M
b0 4
b0 O
b0 8
b0 e
b0 5
b0 D
b0 N
b0 \
b0 ,
b0 a
b10000 -
b10000 `
b0 7
b0 J
b1001100 /
b1001100 L
b1001100 P
b10000000010011001100 3
b10000000010011001100 U
b100100 :
b100100 Q
b101000 !
b101000 &
b101000 .
b101000 S
b101000 T
b101000 _
b101000 R
1#
#110000
0#
#115000
b111101 B
b111101 G
b111101 M
b10 7
b10 J
b10000010010011001100 3
b10000010010011001100 U
b101000 :
b101000 Q
b101100 !
b101100 &
b101100 .
b101100 S
b101100 T
b101100 _
b101100 R
1#
#120000
0#
#125000
b111011 B
b111011 G
b111011 M
b100 7
b100 J
b10000100010011001100 3
b10000100010011001100 U
b101100 :
b101100 Q
b110000 !
b110000 &
b110000 .
b110000 S
b110000 T
b110000 _
b110000 R
1#
#130000
0#
#135000
b111001 B
b111001 G
b111001 M
b110 7
b110 J
b10000110010011001100 3
b10000110010011001100 U
b110000 :
b110000 Q
b110100 !
b110100 &
b110100 .
b110100 S
b110100 T
b110100 _
b110100 R
1#
#140000
0#
#145000
b111111 B
b111111 G
b111111 M
b10001 -
b10001 `
b0 7
b0 J
b10001000010011001100 3
b10001000010011001100 U
b110100 :
b110100 Q
b111000 !
b111000 &
b111000 .
b111000 S
b111000 T
b111000 _
b111000 R
1#
#150000
0#
#155000
b111101 B
b111101 G
b111101 M
b10 7
b10 J
b10001010010011001100 3
b10001010010011001100 U
b111000 :
b111000 Q
b111100 !
b111100 &
b111100 .
b111100 S
b111100 T
b111100 _
b111100 R
1#
#160000
0#
#165000
b111011 B
b111011 G
b111011 M
b100 7
b100 J
b10001100010011001100 3
b10001100010011001100 U
b111100 :
b111100 Q
b1000000 !
b1000000 &
b1000000 .
b1000000 S
b1000000 T
b1000000 _
b1000000 R
1#
#170000
0#
#175000
b0 B
b0 G
b0 M
b110 7
b110 J
b1001101 /
b1001101 L
b1001101 P
b10001110010011001101 3
b10001110010011001101 U
b1000000 :
b1000000 Q
b1000100 !
b1000100 &
b1000100 .
b1000100 S
b1000100 T
b1000100 _
b1000100 R
1#
#180000
0#
#185000
12
b10 -
b10 `
b0 7
b0 J
b1010101 /
b1010101 L
b1010101 P
b10000001001010101 3
b10000001001010101 U
b1000100 :
b1000100 Q
b1001000 !
b1001000 &
b1001000 .
b1001000 S
b1001000 T
b1001000 _
b1001000 R
1#
#190000
0#
#195000
1;
02
b10 7
b10 J
b10010001001010101 3
b10010001001010101 U
b1001000 :
b1001000 Q
b1001100 !
b1001100 &
b1001100 .
b1001100 S
b1001100 T
b1001100 _
b1001100 R
1#
#200000
0#
#205000
1<
0;
b100 7
b100 J
b10100001001010101 3
b10100001001010101 U
b1001100 :
b1001100 Q
b1010000 !
b1010000 &
b1010000 .
b1010000 S
b1010000 T
b1010000 _
b1010000 R
1#
#210000
0#
#215000
1>
0<
b110 7
b110 J
b10110001001010101 3
b10110001001010101 U
b1010000 :
b1010000 Q
b1010100 !
b1010100 &
b1010100 .
b1010100 S
b1010100 T
b1010100 _
b1010100 R
1#
#220000
0#
#225000
12
0>
b11 -
b11 `
b0 7
b0 J
b11000001001010101 3
b11000001001010101 U
b1010100 :
b1010100 Q
1C
b1011000 !
b1011000 &
b1011000 .
b1011000 S
b1011000 T
b1011000 _
b1011000 R
1#
#230000
0#
#235000
b1000 I
02
b1000 4
b1000 O
b1000 8
b1000 e
b1000 5
b1000 D
b1000 N
b1000 \
b1000 ,
b1000 a
b10 -
b10 `
b110011 /
b110011 L
b110011 P
b100000010000001010110011 3
b100000010000001010110011 U
b1011000 :
b1011000 Q
b0 !
b0 &
b0 .
b0 S
b0 T
b0 _
0C
1#
#240000
0#
#245000
b10 B
b10 G
b10 M
b10 7
b10 J
b100000010010001010110011 3
b100000010010001010110011 U
b0 :
b0 Q
b100 !
b100 &
b100 .
b100 S
b100 T
b100 _
b100 R
1#
#250000
0#
#255000
b100 B
b100 G
b100 M
b100 7
b100 J
b100000010100001010110011 3
b100000010100001010110011 U
b100 :
b100 Q
b1000 !
b1000 &
b1000 .
b1000 S
b1000 T
b1000 _
b1000 R
1#
#260000
0#
#265000
b110 B
b110 G
b110 M
b110 7
b110 J
b100000010110001010110011 3
b100000010110001010110011 U
b1000 :
b1000 Q
b1100 !
b1100 &
b1100 .
b1100 S
b1100 T
b1100 _
b1100 R
1#
#270000
0#
#275000
b0 B
b0 G
b0 M
b11 -
b11 `
b0 7
b0 J
b100000011000001010110011 3
b100000011000001010110011 U
b1100 :
b1100 Q
b10000 !
b10000 &
b10000 .
b10000 S
b10000 T
b10000 _
b10000 R
1#
#280000
0#
#285000
b10 B
b10 G
b10 M
b10 7
b10 J
b100000011010001010110011 3
b100000011010001010110011 U
b10000 :
b10000 Q
b10100 !
b10100 &
b10100 .
b10100 S
b10100 T
b10100 _
b10100 R
1#
#290000
0#
#295000
b100 B
b100 G
b100 M
b100 7
b100 J
b100000011100001010110011 3
b100000011100001010110011 U
b10100 :
b10100 Q
b11000 !
b11000 &
b11000 .
b11000 S
b11000 T
b11000 _
b11000 R
1#
#300000
0#
#305000
b110 B
b110 G
b110 M
b110 7
b110 J
b100000011110001010110011 3
b100000011110001010110011 U
b11000 :
b11000 Q
b11100 !
b11100 &
b11100 .
b11100 S
b11100 T
b11100 _
b11100 R
1#
#310000
0#
#315000
b100 B
b100 G
b100 M
b10 -
b10 `
b100 7
b100 J
b100000010100001010110011 3
b100000010100001010110011 U
b11100 :
b11100 Q
b100000 !
b100000 &
b100000 .
b100000 S
b100000 T
b100000 _
b100000 R
1#
#320000
0#
#325000
b110 B
b110 G
b110 M
b110 7
b110 J
b100000010110001010110011 3
b100000010110001010110011 U
b100000 :
b100000 Q
b100100 !
b100100 &
b100100 .
b100100 S
b100100 T
b100100 _
b100100 R
1#
#330000
0#
#335000
b0 I
b111111 B
b111111 G
b111111 M
b0 4
b0 O
b0 8
b0 e
b0 5
b0 D
b0 N
b0 \
b0 ,
b0 a
b10000 -
b10000 `
b0 7
b0 J
b1001100 /
b1001100 L
b1001100 P
b10000000010011001100 3
b10000000010011001100 U
b100100 :
b100100 Q
b101000 !
b101000 &
b101000 .
b101000 S
b101000 T
b101000 _
b101000 R
1#
#340000
0#
#345000
b111101 B
b111101 G
b111101 M
b10 7
b10 J
b10000010010011001100 3
b10000010010011001100 U
b101000 :
b101000 Q
b101100 !
b101100 &
b101100 .
b101100 S
b101100 T
b101100 _
b101100 R
1#
#350000
0#
#355000
b111011 B
b111011 G
b111011 M
b100 7
b100 J
b10000100010011001100 3
b10000100010011001100 U
b101100 :
b101100 Q
b110000 !
b110000 &
b110000 .
b110000 S
b110000 T
b110000 _
b110000 R
1#
